severino/__init__.py
severino/sdk/__init__.py
severino/sdk/airflow/__init__.py
severino/sdk/airflow/airflow.py
severino/sdk/greenhouse/bot.py
severino/sdk/helpers/__init__.py
severino/sdk/helpers/http_requests.py
severino/sdk/helpers/models.py
severino/sdk/helpers/pagination.py
severino/sdk/hub_distance/__init__.py
severino/sdk/hub_distance/hub_distance.py
severino/sdk/internal_recruitment/__init__.py
severino/sdk/internal_recruitment/internal_recruitment.py
severino/sdk/mail_carrier/__init__.py
severino/sdk/mail_carrier/mail_carrier.py
severino/sdk/reports_of_pcds_in_admission/__init__.py
severino/sdk/reports_of_pcds_in_admission/reports_of_pcds_in_admission.py
severino/sdk/rescission_workflow/__init__.py
severino/sdk/rescission_workflow/rescission_workflow.py
severino/sdk/store_data/__init__.py
severino/sdk/store_data/store_data.py
severino/sdk/store_data/store_data_tmp.py
severino/sdk/vagas_dot_com/__init__.py
severino/sdk/vagas_dot_com/bot.py
severino/settings.py
severino-0.17.0.dist-info/METADATA
severino-0.17.0.dist-info/WHEEL
severino-0.17.0.dist-info/RECORD
