Metadata-Version: 2.1
Name: severino
Version: 0.17.0
Summary: O Severino é utilizado para facilitar as integrações e também a reutilização de código das aplicações de People Analytics da Stone.
Author: Stone People Analytics
Author-email: systems-techpeople@stone.com.br
Requires-Python: >=3.9,<4.0
Classifier: Programming Language :: Python :: 3
Classifier: Programming Language :: Python :: 3.9
Classifier: Programming Language :: Python :: 3.10
Classifier: Programming Language :: Python :: 3.11
Requires-Dist: Jinja2 (>=3.0.3,<4.0.0)
Requires-Dist: requests (>=2.27.1,<3.0.0)
